nldcsc/__init__.py
nldcsc/__main__.py
nldcsc/cli.py
nldcsc/auth/README.md
nldcsc/auth/__init__.py
nldcsc/auth/ldap_client.py
nldcsc/custom_types/__init__.py
nldcsc/custom_types/sqlalchemy/__init__.py
nldcsc/custom_types/sqlalchemy/annotations.py
nldcsc/custom_types/sqlalchemy/custom_types.py
nldcsc/custom_types/sqlalchemy/model_base.py
nldcsc/datatables/__init__.py
nldcsc/datatables/server_side_dt.py
nldcsc/datatables/server_side_dt_es.py
nldcsc/datatables/server_side_dt_sql.py
nldcsc/flask_managers/README.md
nldcsc/flask_managers/__init__.py
nldcsc/flask_managers/flask_app_manager.py
nldcsc/flask_midddleware/__init__.py
nldcsc/flask_midddleware/base.py
nldcsc/flask_midddleware/debug_logging.py
nldcsc/flask_midddleware/middleware_manager.py
nldcsc/flask_plugins/README.md
nldcsc/flask_plugins/__init__.py
nldcsc/flask_plugins/flask_eswrap.py
nldcsc/flask_plugins/flask_kafka.py
nldcsc/flask_plugins/flask_redis.py
nldcsc/flask_plugins/flask_sql_migrate/README.md
nldcsc/flask_plugins/flask_sql_migrate/__init__.py
nldcsc/flask_plugins/flask_sql_migrate/cli.py
nldcsc/flask_plugins/flask_sql_migrate/templates/aioflask/README
nldcsc/flask_plugins/flask_sql_migrate/templates/aioflask/alembic.ini.mako
nldcsc/flask_plugins/flask_sql_migrate/templates/aioflask/script.py.mako
nldcsc/flask_plugins/flask_sql_migrate/templates/aioflask-multidb/README
nldcsc/flask_plugins/flask_sql_migrate/templates/aioflask-multidb/alembic.ini.mako
nldcsc/flask_plugins/flask_sql_migrate/templates/aioflask-multidb/script.py.mako
nldcsc/flask_plugins/flask_sql_migrate/templates/flask/README
nldcsc/flask_plugins/flask_sql_migrate/templates/flask/alembic.ini.mako
nldcsc/flask_plugins/flask_sql_migrate/templates/flask/script.py.mako
nldcsc/flask_plugins/flask_sql_migrate/templates/flask-multidb/README
nldcsc/flask_plugins/flask_sql_migrate/templates/flask-multidb/alembic.ini.mako
nldcsc/flask_plugins/flask_sql_migrate/templates/flask-multidb/script.py.mako
nldcsc-0.3.68.dist-info/licenses/LICENSE
nldcsc-0.3.68.dist-info/METADATA
nldcsc-0.3.68.dist-info/WHEEL
nldcsc-0.3.68.dist-info/entry_points.txt
nldcsc-0.3.68.dist-info/top_level.txt
nldcsc-0.3.68.dist-info/RECORD
