Metadata-Version: 2.4
Name: nldcsc
Version: 0.3.68
Summary: Package with general devops code
Home-page: https://github.com/NLDCSC/nldcsc
Author: NLDCSC
Author-email: NLDCSC@invalid.com
License: GNU General Public License v3.0
Project-URL: Code, https://github.com/NLDCSC/nldcsc
Platform: any
Classifier: Development Status :: 5 - Production/Stable
Classifier: License :: OSI Approved :: GNU General Public License v3 or later (GPLv3+)
Classifier: Programming Language :: Python
Classifier: Programming Language :: Python :: 3 :: Only
Classifier: Programming Language :: Python :: 3.10
Classifier: Programming Language :: Python :: 3.11
Classifier: Operating System :: OS Independent
Requires-Python: >=3.10,<4.0
License-File: LICENSE
Requires-Dist: setuptools>=68.1.0
Provides-Extra: plugin-sql-migrate
Requires-Dist: sqlalchemy>=2.0.21; extra == "plugin-sql-migrate"
Requires-Dist: alembic==1.13.2; extra == "plugin-sql-migrate"
Requires-Dist: tabulate==0.9.0; extra == "plugin-sql-migrate"
Requires-Dist: dataclasses-json>=0.6.7; extra == "plugin-sql-migrate"
Provides-Extra: mysql
Requires-Dist: pymysql>=1.1.0; extra == "mysql"
Requires-Dist: mysqlclient>=2.1.1; extra == "mysql"
Provides-Extra: plugin-geo-ip
Requires-Dist: aiohttp>=3.10.9; extra == "plugin-geo-ip"
Requires-Dist: pygelf>=0.4.2; extra == "plugin-geo-ip"
Requires-Dist: aiofiles<26.0.0,>=25.1.0; extra == "plugin-geo-ip"
Requires-Dist: gunicorn>=21.2.0; extra == "plugin-geo-ip"
Requires-Dist: ansicolors>=1.1.8; extra == "plugin-geo-ip"
Requires-Dist: httpx[http2]>=0.27.0; extra == "plugin-geo-ip"
Provides-Extra: sso
Requires-Dist: authlib>=1.6.5; extra == "sso"
Requires-Dist: flask>=2.3.3; extra == "sso"
Requires-Dist: pyjwt>=2.8.0; extra == "sso"
Provides-Extra: flask-plugins
Requires-Dist: redis>=4.6.0; extra == "flask-plugins"
Requires-Dist: tabulate==0.9.0; extra == "flask-plugins"
Requires-Dist: dataclasses-json>=0.6.7; extra == "flask-plugins"
Requires-Dist: eswrap>=0.5.0; extra == "flask-plugins"
Requires-Dist: kafka-python>=2.0.2; extra == "flask-plugins"
Requires-Dist: flask-migrate>=4.0.5; extra == "flask-plugins"
Requires-Dist: elasticsearch>=8.7.0; extra == "flask-plugins"
Requires-Dist: flask>=2.3.3; extra == "flask-plugins"
Requires-Dist: alembic==1.13.2; extra == "flask-plugins"
Requires-Dist: sqlalchemy>=2.0.21; extra == "flask-plugins"
Requires-Dist: flask-sqlalchemy>=3.1.1; extra == "flask-plugins"
Requires-Dist: werkzeug>=2.3.7; extra == "flask-plugins"
Provides-Extra: flask-middleware
Requires-Dist: pymysql>=1.1.0; extra == "flask-middleware"
Requires-Dist: flask-sqlalchemy>=3.1.1; extra == "flask-middleware"
Requires-Dist: flask-migrate>=4.0.5; extra == "flask-middleware"
Requires-Dist: mysqlclient>=2.1.1; extra == "flask-middleware"
Requires-Dist: flask>=2.3.3; extra == "flask-middleware"
Requires-Dist: pygelf>=0.4.2; extra == "flask-middleware"
Requires-Dist: gunicorn>=21.2.0; extra == "flask-middleware"
Requires-Dist: pyopenssl>=23.2.0; extra == "flask-middleware"
Requires-Dist: ansicolors>=1.1.8; extra == "flask-middleware"
Requires-Dist: flask-socketio>=5.3.6; extra == "flask-middleware"
Requires-Dist: werkzeug>=2.3.7; extra == "flask-middleware"
Requires-Dist: rfc3339>=6.2; extra == "flask-middleware"
Provides-Extra: cache-redis
Requires-Dist: redis>=5.0.0; extra == "cache-redis"
Provides-Extra: plugin-doh
Requires-Dist: netaddr>=1.3.0; extra == "plugin-doh"
Requires-Dist: pygelf>=0.4.2; extra == "plugin-doh"
Requires-Dist: gunicorn>=21.2.0; extra == "plugin-doh"
Requires-Dist: aiofiles<26.0.0,>=25.1.0; extra == "plugin-doh"
Requires-Dist: dataclasses-json>=0.6.7; extra == "plugin-doh"
Requires-Dist: ansicolors>=1.1.8; extra == "plugin-doh"
Requires-Dist: httpx[http2]>=0.27.0; extra == "plugin-doh"
Provides-Extra: httpx-apis
Requires-Dist: httpx[http2]>=0.27.0; extra == "httpx-apis"
Requires-Dist: aiofiles<26.0.0,>=25.1.0; extra == "httpx-apis"
Provides-Extra: loggers
Requires-Dist: gunicorn>=21.2.0; extra == "loggers"
Requires-Dist: ansicolors>=1.1.8; extra == "loggers"
Requires-Dist: pygelf>=0.4.2; extra == "loggers"
Provides-Extra: plugin-redis
Requires-Dist: redis>=4.6.0; extra == "plugin-redis"
Provides-Extra: plugin-whoisxml
Requires-Dist: requests>=2.31.0; extra == "plugin-whoisxml"
Requires-Dist: pygelf>=0.4.2; extra == "plugin-whoisxml"
Requires-Dist: dataclasses-json>=0.6.7; extra == "plugin-whoisxml"
Requires-Dist: gunicorn>=21.2.0; extra == "plugin-whoisxml"
Requires-Dist: ansicolors>=1.1.8; extra == "plugin-whoisxml"
Provides-Extra: sql-migrations
Requires-Dist: flask>=2.3.3; extra == "sql-migrations"
Requires-Dist: pymysql>=1.1.0; extra == "sql-migrations"
Requires-Dist: pygelf>=0.4.2; extra == "sql-migrations"
Requires-Dist: gunicorn>=21.2.0; extra == "sql-migrations"
Requires-Dist: ansicolors>=1.1.8; extra == "sql-migrations"
Requires-Dist: flask-sqlalchemy>=3.1.1; extra == "sql-migrations"
Requires-Dist: flask-migrate>=4.0.5; extra == "sql-migrations"
Requires-Dist: mysqlclient>=2.1.1; extra == "sql-migrations"
Provides-Extra: flask-managers
Requires-Dist: pymysql>=1.1.0; extra == "flask-managers"
Requires-Dist: flask-sqlalchemy>=3.1.1; extra == "flask-managers"
Requires-Dist: flask-migrate>=4.0.5; extra == "flask-managers"
Requires-Dist: mysqlclient>=2.1.1; extra == "flask-managers"
Requires-Dist: flask>=2.3.3; extra == "flask-managers"
Requires-Dist: pygelf>=0.4.2; extra == "flask-managers"
Requires-Dist: gunicorn>=21.2.0; extra == "flask-managers"
Requires-Dist: pyopenssl>=23.2.0; extra == "flask-managers"
Requires-Dist: ansicolors>=1.1.8; extra == "flask-managers"
Requires-Dist: flask-socketio>=5.3.6; extra == "flask-managers"
Requires-Dist: werkzeug>=2.3.7; extra == "flask-managers"
Provides-Extra: plugin-mailgun
Requires-Dist: requests>=2.31.0; extra == "plugin-mailgun"
Requires-Dist: pydantic>=2.11.7; extra == "plugin-mailgun"
Provides-Extra: http-apis
Requires-Dist: requests>=2.31.0; extra == "http-apis"
Provides-Extra: auth
Requires-Dist: pygelf>=0.4.2; extra == "auth"
Requires-Dist: gunicorn>=21.2.0; extra == "auth"
Requires-Dist: ansicolors>=1.1.8; extra == "auth"
Requires-Dist: click==8.1.7; extra == "auth"
Requires-Dist: python-ldap>=3.4.3; extra == "auth"
Provides-Extra: custom-type-sqlalchemy
Requires-Dist: sqlalchemy>=2.0.21; extra == "custom-type-sqlalchemy"
Provides-Extra: datatables
Requires-Dist: redis>=4.6.0; extra == "datatables"
Requires-Dist: tabulate==0.9.0; extra == "datatables"
Requires-Dist: dataclasses-json>=0.6.7; extra == "datatables"
Requires-Dist: eswrap>=0.5.0; extra == "datatables"
Requires-Dist: kafka-python>=2.0.2; extra == "datatables"
Requires-Dist: flask-migrate>=4.0.5; extra == "datatables"
Requires-Dist: elasticsearch>=8.7.0; extra == "datatables"
Requires-Dist: flask>=2.3.3; extra == "datatables"
Requires-Dist: alembic==1.13.2; extra == "datatables"
Requires-Dist: sqlalchemy>=2.0.21; extra == "datatables"
Requires-Dist: flask-sqlalchemy>=3.1.1; extra == "datatables"
Requires-Dist: werkzeug>=2.3.7; extra == "datatables"
Provides-Extra: plugins
Requires-Dist: netaddr>=1.3.0; extra == "plugins"
Requires-Dist: redis>=4.6.0; extra == "plugins"
Requires-Dist: requests>=2.31.0; extra == "plugins"
Requires-Dist: tabulate==0.9.0; extra == "plugins"
Requires-Dist: aiofiles<26.0.0,>=25.1.0; extra == "plugins"
Requires-Dist: dataclasses-json>=0.6.7; extra == "plugins"
Requires-Dist: aiohttp>=3.10.9; extra == "plugins"
Requires-Dist: alembic==1.13.2; extra == "plugins"
Requires-Dist: pygelf>=0.4.2; extra == "plugins"
Requires-Dist: sqlalchemy>=2.0.21; extra == "plugins"
Requires-Dist: pydantic>=2.11.7; extra == "plugins"
Requires-Dist: gunicorn>=21.2.0; extra == "plugins"
Requires-Dist: ansicolors>=1.1.8; extra == "plugins"
Requires-Dist: httpx[http2]>=0.27.0; extra == "plugins"
Provides-Extra: custom-types
Requires-Dist: sqlalchemy>=2.0.21; extra == "custom-types"
Provides-Extra: plugin-limit
Requires-Dist: redis>=4.6.0; extra == "plugin-limit"
Provides-Extra: redis-cache
Requires-Dist: redis>=5.0.0; extra == "redis-cache"
Provides-Extra: all
Requires-Dist: dataclasses-json>=0.6.7; extra == "all"
Requires-Dist: eswrap>=0.5.0; extra == "all"
Requires-Dist: kafka-python>=2.0.2; extra == "all"
Requires-Dist: pydantic>=2.11.7; extra == "all"
Requires-Dist: pyopenssl>=23.2.0; extra == "all"
Requires-Dist: httpx[http2]>=0.27.0; extra == "all"
Requires-Dist: flask-socketio>=5.3.6; extra == "all"
Requires-Dist: werkzeug>=2.3.7; extra == "all"
Requires-Dist: rfc3339>=6.2; extra == "all"
Requires-Dist: redis>=4.6.0; extra == "all"
Requires-Dist: requests>=2.31.0; extra == "all"
Requires-Dist: authlib>=1.6.5; extra == "all"
Requires-Dist: python-ldap>=3.4.3; extra == "all"
Requires-Dist: aiohttp>=3.10.9; extra == "all"
Requires-Dist: sqlalchemy>=2.0.21; extra == "all"
Requires-Dist: ansicolors>=1.1.8; extra == "all"
Requires-Dist: click==8.1.7; extra == "all"
Requires-Dist: netaddr>=1.3.0; extra == "all"
Requires-Dist: tabulate==0.9.0; extra == "all"
Requires-Dist: pymysql>=1.1.0; extra == "all"
Requires-Dist: flask-migrate>=4.0.5; extra == "all"
Requires-Dist: elasticsearch>=8.7.0; extra == "all"
Requires-Dist: alembic==1.13.2; extra == "all"
Requires-Dist: flask>=2.3.3; extra == "all"
Requires-Dist: flask-sqlalchemy>=3.1.1; extra == "all"
Requires-Dist: pyjwt>=2.8.0; extra == "all"
Requires-Dist: aiofiles<26.0.0,>=25.1.0; extra == "all"
Requires-Dist: redis>=5.0.0; extra == "all"
Requires-Dist: mysqlclient>=2.1.1; extra == "all"
Requires-Dist: pygelf>=0.4.2; extra == "all"
Requires-Dist: gunicorn>=21.2.0; extra == "all"
Dynamic: author
Dynamic: author-email
Dynamic: classifier
Dynamic: description
Dynamic: description-content-type
Dynamic: home-page
Dynamic: license
Dynamic: license-file
Dynamic: platform
Dynamic: project-url
Dynamic: provides-extra
Dynamic: requires-dist
Dynamic: requires-python
Dynamic: summary
